mechanician_arangodb/__init__.py
mechanician_arangodb/doc_mgr_instructions.py
mechanician_arangodb/doc_mgr_tool_instructions.py
mechanician_arangodb/document_ai_tools.py
mechanician_arangodb/document_manager.py
mechanician_arangodb/notepad_store.py
mechanician_arangodb-0.1.3.dist-info/METADATA
mechanician_arangodb-0.1.3.dist-info/WHEEL
mechanician_arangodb-0.1.3.dist-info/top_level.txt
mechanician_arangodb-0.1.3.dist-info/RECORD
