Metadata-Version: 2.1
Name: mechanician-arangodb
Version: 0.1.3
Summary: Daring Mechanician AITools for interacting with ArangoDB Graph Databases.
Home-page: https://github.com/liebke/mechanician
Author: David Edgar Liebke
Author-email: david@gmail.com
Requires-Dist: mechanician >=0.1.3
Requires-Dist: python-arango >=5.0.0
